collocation/__init__.py
collocation/association.py
collocation/collocation.py
collocation/fisher_exact.py
collocation-0.0.6.dist-info/METADATA
collocation-0.0.6.dist-info/WHEEL
collocation-0.0.6.dist-info/top_level.txt
collocation-0.0.6.dist-info/RECORD
